MANIFEST.in
README.md
setup.cfg
setup.py
farnsworth/__init__.py
farnsworth/fusor.py
farnsworth.egg-info/PKG-INFO
farnsworth.egg-info/SOURCES.txt
farnsworth.egg-info/dependency_links.txt
farnsworth.egg-info/not-zip-safe
farnsworth.egg-info/requires.txt
farnsworth.egg-info/top_level.txt
farnsworth/js/react-dom-server.min.js
farnsworth/js/react-dom.min.js
farnsworth/js/react.min.js
farnsworth/js/util.js
farnsworth/tests/input/simple_element.js
farnsworth/tests/output/simple_element.html