Metadata-Version: 1.1
Name: farnsworth
Version: 0.0.1
Summary: A small Python library for rendering React components.
Home-page: http://github.com/jvalinsky/farnsworth
Author: Jack Valinsky
Author-email: jvalinsk@u.rochester.edu
License: MIT
Download-URL: https://github.com/jvalinsky/farnsworth/archive/0.0.1.tar.gz
Keywords: react,server-side rendering,web
Platform: UNKNOWN
